lpsim/__init__.py
lpsim/_version.py
lpsim/consts.py
lpsim/responses.py
lpsim/tools.py
lpsim/agents/__init__.py
lpsim/agents/agent_base.py
lpsim/agents/interaction_agent.py
lpsim/agents/nothing_agent.py
lpsim/agents/random_agent.py
lpsim/network/__init__.py
lpsim/network/__version__.py
lpsim/network/http_room_server.py
lpsim/network/http_server.py
lpsim/network/utils.py
lpsim/resources/consts.py
lpsim/server/__init__.py
lpsim/server/action.py
lpsim/server/consts.py
lpsim/server/deck.py
lpsim/server/dice.py
lpsim/server/elemental_reaction.py
lpsim/server/event.py
lpsim/server/event_controller.py
lpsim/server/event_handler.py
lpsim/server/interaction.py
lpsim/server/match.py
lpsim/server/modifiable_values.py
lpsim/server/object_base.py
lpsim/server/player_table.py
lpsim/server/query.py
lpsim/server/struct.py
lpsim/server/card/__init__.py
lpsim/server/card/equipment/__init__.py
lpsim/server/card/equipment/artifact/__init__.py
lpsim/server/card/equipment/artifact/base.py
lpsim/server/card/equipment/artifact/element_artifacts.py
lpsim/server/card/equipment/artifact/emblem_of_severed_fate.py
lpsim/server/card/equipment/artifact/exile.py
lpsim/server/card/equipment/artifact/gamblers.py
lpsim/server/card/equipment/artifact/gilded_dreams.py
lpsim/server/card/equipment/artifact/heal_by_skill.py
lpsim/server/card/equipment/artifact/instructors_cap.py
lpsim/server/card/equipment/artifact/millelith.py
lpsim/server/card/equipment/artifact/ocean_hued.py
lpsim/server/card/equipment/artifact/vermillion_shimenawa.py
lpsim/server/card/equipment/weapon/__init__.py
lpsim/server/card/equipment/weapon/base.py
lpsim/server/card/equipment/weapon/favonius.py
lpsim/server/card/equipment/weapon/other_bow.py
lpsim/server/card/equipment/weapon/other_catalyst.py
lpsim/server/card/equipment/weapon/other_claymore.py
lpsim/server/card/equipment/weapon/other_polearm.py
lpsim/server/card/equipment/weapon/other_sword.py
lpsim/server/card/equipment/weapon/sacrificial.py
lpsim-0.4.5.1.dist-info/LICENSE
lpsim-0.4.5.1.dist-info/METADATA
lpsim-0.4.5.1.dist-info/WHEEL
lpsim-0.4.5.1.dist-info/top_level.txt
lpsim-0.4.5.1.dist-info/RECORD
