Metadata-Version: 2.1
Name: lpsim
Version: 0.4.5.1
Summary: Lochfolk Prinzessin Simulator, which simulates Genius Invokation TCG
Author-email: Zyr17 <jzjqz17@gmail.com>
Project-URL: Homepage, https://github.com/LPSim/backend
Project-URL: Bug Tracker, https://github.com/LPSim/backend/issues
Classifier: Programming Language :: Python :: 3
Classifier: License :: OSI Approved :: GNU Affero General Public License v3 or later (AGPLv3+)
Classifier: Operating System :: OS Independent
Classifier: Programming Language :: Python :: 3.10
Requires-Python: >=3.10
License-File: LICENSE
Requires-Dist: pydantic ==1.10.14
Requires-Dist: typing-extensions
Requires-Dist: dictdiffer
Requires-Dist: fastapi
Requires-Dist: uvicorn[standard]
Provides-Extra: dev
Requires-Dist: build ; extra == 'dev'
Requires-Dist: numpy ; extra == 'dev'
Requires-Dist: setuptools-scm ; extra == 'dev'
Requires-Dist: pytest ; extra == 'dev'
Requires-Dist: pytest-cov ; extra == 'dev'
Requires-Dist: pytest-xdist ; extra == 'dev'
Requires-Dist: pyright ; extra == 'dev'
